ereg/__init__.py
ereg/cli/__init__.py
ereg/cli/run.py
ereg/configurations/default_rigid.yaml
ereg/configurations/sample_config.yaml
ereg/functional.py
ereg/registration.py
ereg/utils/__init__.py
ereg/utils/citation_reminder.py
ereg/utils/io.py
ereg/utils/metrics.py
ereg-0.0.10.dist-info/LICENSE
ereg-0.0.10.dist-info/METADATA
ereg-0.0.10.dist-info/WHEEL
ereg-0.0.10.dist-info/entry_points.txt
ereg-0.0.10.dist-info/RECORD
